pyrosettacolabsetup/__init__.py
pyrosettacolabsetup-1.0.9.dist-info/LICENSE
pyrosettacolabsetup-1.0.9.dist-info/METADATA
pyrosettacolabsetup-1.0.9.dist-info/WHEEL
pyrosettacolabsetup-1.0.9.dist-info/top_level.txt
pyrosettacolabsetup-1.0.9.dist-info/RECORD
