Metadata-Version: 2.1
Name: pyrosettacolabsetup
Version: 1.0.9
Summary: Mounts Google Drive for PyRosetta use in Google Colaboratory
Home-page: https://github.com/RosettaCommons/pyrosetta_colab_setup
Author: Sergey Lyskov
Author-email: sergey.lyskov@jhu.edu
License: MIT
License-File: LICENSE
